tottag/1_convert_to_csv.py
tottag/1_tottags_batch.py
tottag/2_convert_to_csv.py
tottag/2_tottags_batch.py
tottag/__init__.py
tottag/experimental_tottag.py
tottag/load_imu_data.py
tottag/parse.py
tottag/processing.py
tottag/quick_download_trigger.py
tottag/segger_download.py
tottag/tkcal.py
tottag/tottag.py
tottag/tottag_dashboard.ico
tottag/tottag_dashboard.png
tottag/trim_pkl.py
tottag-1.1.0.dist-info/METADATA
tottag-1.1.0.dist-info/WHEEL
tottag-1.1.0.dist-info/entry_points.txt
tottag-1.1.0.dist-info/top_level.txt
tottag-1.1.0.dist-info/RECORD
