Metadata-Version: 2.4
Name: tottag
Version: 1.1.0
Summary: TotTag Management Dashboard
Home-page: https://github.com/lab11/socitrack
Author: Will Hedgecock
Author-email: ronald.w.hedgecock@vanderbilt.edu
Classifier: Programming Language :: Python :: 3
Classifier: Operating System :: OS Independent
Requires-Python: >=3.8
Requires-Dist: bleak
Requires-Dist: matplotlib
Requires-Dist: numpy
Requires-Dist: pandas
Requires-Dist: pytz
Requires-Dist: scipy
Requires-Dist: pyserial
Requires-Dist: babel
Requires-Dist: tzlocal
Requires-Dist: tk
Dynamic: author
Dynamic: author-email
Dynamic: classifier
Dynamic: description
Dynamic: description-content-type
Dynamic: home-page
Dynamic: requires-dist
Dynamic: requires-python
Dynamic: summary
